polarspulse/__init__.py
polarspulse/profiling.py
polarspulse-0.1.0.dist-info/licenses/LICENSE
polarspulse-0.1.0.dist-info/METADATA
polarspulse-0.1.0.dist-info/WHEEL
polarspulse-0.1.0.dist-info/top_level.txt
polarspulse-0.1.0.dist-info/RECORD
