Metadata-Version: 2.4
Name: polarspulse
Version: 0.1.0
Summary: Fast, insightful data profiling for Polars DataFrames.
Author-email: ark4dev <akram.alyass@example.com>
License: MIT License
Project-URL: Homepage, https://github.com/ark4dev/polarspulse
Project-URL: Bug Tracker, https://github.com/ark4dev/polarspulse/issues
Keywords: data profiling,data analysis,polars,data science,data visualization,data exploration,data quality,data validation,data insights,data statistics
Classifier: Programming Language :: Python :: 3
Classifier: Programming Language :: Python :: 3.8
Classifier: Programming Language :: Python :: 3.9
Classifier: Programming Language :: Python :: 3.10
Classifier: Programming Language :: Python :: 3.11
Classifier: Programming Language :: Python :: 3.12
Classifier: License :: OSI Approved :: MIT License
Classifier: Operating System :: OS Independent
Classifier: Intended Audience :: Developers
Classifier: Intended Audience :: Science/Research
Classifier: Topic :: Scientific/Engineering :: Information Analysis
Classifier: Topic :: Software Development :: Libraries :: Python Modules
Classifier: Typing :: Typed
Requires-Python: >=3.8
License-File: LICENSE
Requires-Dist: polars>=1.26.0
Dynamic: license-file
